{
  "schema_version": "dossier-1",
  "source": {
    "title": "Approaches to modeling train scheduling problems as job-shop problems with blocking constraints",
    "doi": "10.1007/s10951-017-0526-0",
    "arxiv_id": null,
    "openalex_id": "W2607795493",
    "authors": [
      "Julia Lange",
      "Frank Werner"
    ],
    "year": 2017,
    "venue": "Journal of Scheduling",
    "publisher": "Springer Science+Business Media",
    "cited_by_count": 49,
    "scopus_cited_by_count": null,
    "api": "openalex",
    "retrieved": "2026-06-21",
    "file_path": null,
    "file_sha256": null,
    "entitlement": null,
    "landing_url": "https://doi.org/10.1007/s10951-017-0526-0"
  },
  "references": [
    {
      "title": "A Survey of Optimization Models for Train Routing and Scheduling",
      "doi": "10.1287/trsc.32.4.380",
      "openalex_id": "W2140764876",
      "year": 1998,
      "cited_by_count": 778,
      "source": "openalex"
    },
    {
      "title": "On the Job-Shop Scheduling Problem",
      "doi": "10.1287/opre.8.2.219",
      "openalex_id": "W2166928920",
      "year": 1960,
      "cited_by_count": 656,
      "source": "openalex"
    },
    {
      "title": "A branch and bound algorithm for scheduling trains in a railway network",
      "doi": "10.1016/j.ejor.2006.10.034",
      "openalex_id": "W2031545009",
      "year": 2006,
      "cited_by_count": 613,
      "source": "openalex"
    },
    {
      "title": "Priority Rules for Job Shops with Weighted Tardiness Costs",
      "doi": "10.1287/mnsc.33.8.1035",
      "openalex_id": "W1972928373",
      "year": 1987,
      "cited_by_count": 571,
      "source": "openalex"
    },
    {
      "title": "Optimizing urban rail timetable under time-dependent demand and oversaturated conditions",
      "doi": "10.1016/j.trc.2013.08.016",
      "openalex_id": "W2077613353",
      "year": 2013,
      "cited_by_count": 512,
      "source": "openalex"
    },
    {
      "title": "Job-shop scheduling with blocking and no-wait constraints",
      "doi": "10.1016/s0377-2217(01)00338-1",
      "openalex_id": "W2028900733",
      "year": 2002,
      "cited_by_count": 473,
      "source": "openalex"
    },
    {
      "title": "Train scheduling for minimizing passenger waiting time with time-dependent demand and skip-stop patterns: Nonlinear integer programming models with linear constraints",
      "doi": "10.1016/j.trb.2015.03.004",
      "openalex_id": "W2068341557",
      "year": 2015,
      "cited_by_count": 450,
      "source": "openalex"
    },
    {
      "title": "An integer linear‐programming model for machine scheduling",
      "doi": "10.1002/nav.3800060205",
      "openalex_id": "W2072298242",
      "year": 1959,
      "cited_by_count": 379,
      "source": "openalex"
    },
    {
      "title": "Railway track allocation: models and methods",
      "doi": "10.1007/s00291-009-0189-0",
      "openalex_id": "W2006192728",
      "year": 2009,
      "cited_by_count": 334,
      "source": "openalex"
    },
    {
      "title": "N-tracked railway traffic re-scheduling during disturbances",
      "doi": "10.1016/j.trb.2006.06.001",
      "openalex_id": "W2016556952",
      "year": 2006,
      "cited_by_count": 299,
      "source": "openalex"
    },
    {
      "title": "A multi-objective train scheduling model and solution",
      "doi": "10.1016/j.trb.2004.02.004",
      "openalex_id": "W2137264502",
      "year": 2004,
      "cited_by_count": 298,
      "source": "openalex"
    },
    {
      "title": "Simultaneous train rerouting and rescheduling on an N-track network: A model reformulation with network-based cumulative flow variables",
      "doi": "10.1016/j.trb.2014.05.005",
      "openalex_id": "W2033454236",
      "year": 2014,
      "cited_by_count": 280,
      "source": "openalex"
    },
    {
      "title": "Reordering and Local Rerouting Strategies to Manage Train Traffic in Real Time",
      "doi": "10.1287/trsc.1080.0247",
      "openalex_id": "W2117316145",
      "year": 2008,
      "cited_by_count": 252,
      "source": "openalex"
    },
    {
      "title": "Scheduling trains on a railway network using a discrete event model of railway traffic",
      "doi": "10.1016/s0191-2615(03)00006-7",
      "openalex_id": "W2011348726",
      "year": 2003,
      "cited_by_count": 235,
      "source": "openalex"
    },
    {
      "title": "A Model, Algorithms and Strategy for Train Pathing",
      "doi": "10.1057/jors.1995.136",
      "openalex_id": "W2024166508",
      "year": 1995,
      "cited_by_count": 220,
      "source": "openalex"
    },
    {
      "title": "A Railway Timetable Rescheduling Approach for Handling Large-Scale Disruptions",
      "doi": "10.1287/trsc.2015.0618",
      "openalex_id": "W2158515881",
      "year": 2015,
      "cited_by_count": 195,
      "source": "openalex"
    },
    {
      "title": "Tactical Scheduling of Rail Operations: The SCAN I System",
      "doi": "10.1287/trsc.25.1.46",
      "openalex_id": "W2054775717",
      "year": 1991,
      "cited_by_count": 194,
      "source": "openalex"
    },
    {
      "title": "International Journal of Operational Research: Advances in Operations Research",
      "doi": null,
      "openalex_id": "W4287478647",
      "year": 2021,
      "cited_by_count": 188,
      "source": "openalex"
    },
    {
      "title": "A fast heuristic for the train scheduling problem",
      "doi": "10.1016/0305-0548(94)90099-x",
      "openalex_id": "W1969564439",
      "year": 1994,
      "cited_by_count": 165,
      "source": "openalex"
    },
    {
      "title": "Heuristic Techniques for Single Line Train Scheduling",
      "doi": "10.1023/a:1009672832658",
      "openalex_id": "W1601279095",
      "year": 1997,
      "cited_by_count": 161,
      "source": "openalex"
    },
    {
      "title": "Train Timetable Problem on a Single-Line Railway With Fuzzy Passenger Demand",
      "doi": "10.1109/tfuzz.2008.924198",
      "openalex_id": "W2113841111",
      "year": 2009,
      "cited_by_count": 131,
      "source": "openalex"
    },
    {
      "title": "A study of integer programming formulations for scheduling problems",
      "doi": "10.1080/00207729708929360",
      "openalex_id": "W2065053103",
      "year": 1997,
      "cited_by_count": 128,
      "source": "openalex"
    },
    {
      "title": "Scheduling trains as a blocking parallel-machine job shop scheduling problem",
      "doi": "10.1016/j.cor.2008.12.012",
      "openalex_id": "W1967184557",
      "year": 2009,
      "cited_by_count": 119,
      "source": "openalex"
    },
    {
      "title": "Efficient scheduling of railway traffic based on global information of train",
      "doi": "10.1016/j.trb.2008.03.003",
      "openalex_id": "W2028265963",
      "year": 2008,
      "cited_by_count": 85,
      "source": "openalex"
    },
    {
      "title": "Computer Aided Train Dispatching: Decision Support Through Optimization",
      "doi": "10.1287/inte.13.6.24",
      "openalex_id": "W2102244366",
      "year": 1983,
      "cited_by_count": 81,
      "source": "openalex"
    },
    {
      "title": "A study on local search neighborhoods for the job shop scheduling problem with total weighted tardiness objective",
      "doi": "10.1016/j.cor.2015.07.011",
      "openalex_id": "W2208878817",
      "year": 2015,
      "cited_by_count": 78,
      "source": "openalex"
    },
    {
      "title": "A disjunctive graph model and framework for constructing new train schedules",
      "doi": "10.1016/j.ejor.2008.12.005",
      "openalex_id": "W1998885613",
      "year": 2008,
      "cited_by_count": 73,
      "source": "openalex"
    },
    {
      "title": "Modeling Network Transition Constraints with Hypergraphs",
      "doi": "10.1287/trsc.1100.0337",
      "openalex_id": "W2033398567",
      "year": 2010,
      "cited_by_count": 70,
      "source": "openalex"
    },
    {
      "title": "A new neighborhood and tabu search for the Blocking Job Shop",
      "doi": "10.1016/j.dam.2009.02.020",
      "openalex_id": "W2067814550",
      "year": 2009,
      "cited_by_count": 66,
      "source": "openalex"
    },
    {
      "title": "Scheduling heterogeneous train traffic on double tracks with efficient dispatching rules",
      "doi": "10.1016/j.trb.2015.05.007",
      "openalex_id": "W621131384",
      "year": 2015,
      "cited_by_count": 39,
      "source": "openalex"
    },
    {
      "title": "The track formulation for the Train Dispatching problem",
      "doi": "10.1016/j.endm.2013.05.138",
      "openalex_id": "W1993136048",
      "year": 2013,
      "cited_by_count": 22,
      "source": "openalex"
    },
    {
      "title": "The TUFF train scheduler: two duration trip scheduling on single track networks",
      "doi": null,
      "openalex_id": "W83297485",
      "year": 1997,
      "cited_by_count": 3,
      "source": "openalex"
    },
    {
      "title": "A Tutorial on Train Timetabling and Train Platforming Problems",
      "doi": null,
      "openalex_id": "W1519845812",
      "year": 2013,
      "cited_by_count": 1,
      "source": "openalex"
    }
  ],
  "cited_by": [
    {
      "title": "A multi-action deep reinforcement learning framework for flexible Job-shop scheduling problem",
      "doi": "10.1016/j.eswa.2022.117796",
      "openalex_id": "W4282946405",
      "year": 2022,
      "cited_by_count": 314,
      "source": "openalex"
    },
    {
      "title": "Train Dispatching Management With Data- Driven Approaches: A Comprehensive Review and Appraisal",
      "doi": "10.1109/access.2019.2935106",
      "openalex_id": "W2969003068",
      "year": 2019,
      "cited_by_count": 69,
      "source": "openalex"
    },
    {
      "title": "Dynamic Scheduling, Operation Control and Their Integration in High-Speed Railways: A Review of Recent Research",
      "doi": "10.1109/tits.2021.3131202",
      "openalex_id": "W4205808488",
      "year": 2021,
      "cited_by_count": 68,
      "source": "openalex"
    },
    {
      "title": "Job shop scheduling with a combination of four buffering constraints",
      "doi": "10.1080/00207543.2017.1401240",
      "openalex_id": "W2770596275",
      "year": 2017,
      "cited_by_count": 41,
      "source": "openalex"
    },
    {
      "title": "Quantum Annealing in the NISQ Era: Railway Conflict Management",
      "doi": "10.3390/e25020191",
      "openalex_id": "W4317423769",
      "year": 2023,
      "cited_by_count": 25,
      "source": "openalex"
    },
    {
      "title": "Quadratic and higher-order unconstrained binary optimization of railway rescheduling for quantum computing",
      "doi": "10.1007/s11128-022-03670-y",
      "openalex_id": "W4297997184",
      "year": 2022,
      "cited_by_count": 24,
      "source": "openalex"
    },
    {
      "title": "Graph-Based Modeling in Shop Scheduling Problems: Review and Extensions",
      "doi": "10.3390/app11114741",
      "openalex_id": "W3164085978",
      "year": 2021,
      "cited_by_count": 24,
      "source": "openalex"
    },
    {
      "title": "Efficient primal heuristic updates for the blocking job shop problem",
      "doi": "10.1016/j.ejor.2021.02.051",
      "openalex_id": "W3138178192",
      "year": 2021,
      "cited_by_count": 23,
      "source": "openalex"
    },
    {
      "title": "On Neighborhood Structures and Repair Techniques for Blocking Job Shop Scheduling Problems",
      "doi": "10.3390/a12110242",
      "openalex_id": "W2983511892",
      "year": 2019,
      "cited_by_count": 16,
      "source": "openalex"
    },
    {
      "title": "Scheduling Extra Train Paths Into Cyclic Timetable Based on the Genetic Algorithm",
      "doi": "10.1109/access.2020.2997777",
      "openalex_id": "W3029660600",
      "year": 2020,
      "cited_by_count": 16,
      "source": "openalex"
    },
    {
      "title": "Quantum computing approach to railway dispatching and conflict management optimization on single-track railway lines",
      "doi": "10.48550/arxiv.2010.08227",
      "openalex_id": "W3093118903",
      "year": 2020,
      "cited_by_count": 14,
      "source": "openalex"
    },
    {
      "title": "A Permutation-Based Heuristic Method for the Blocking Job Shop Scheduling Problem",
      "doi": "10.1016/j.ifacol.2019.11.395",
      "openalex_id": "W2998184217",
      "year": 2019,
      "cited_by_count": 12,
      "source": "openalex"
    },
    {
      "title": "A Deep Reinforcement Learning Approach for the Traffic Management of High-Speed Railways",
      "doi": "10.1109/itsc48978.2021.9564794",
      "openalex_id": "W3208801615",
      "year": 2021,
      "cited_by_count": 10,
      "source": "openalex"
    },
    {
      "title": "A Hybrid Estimation-of-Distribution Algorithm for Scheduling Flexible Job Shop With Limited Buffers Based on Petri Nets",
      "doi": "10.1109/access.2020.3022655",
      "openalex_id": "W3084231098",
      "year": 2020,
      "cited_by_count": 10,
      "source": "openalex"
    },
    {
      "title": "Two-Machine Job-Shop Scheduling with Equal Processing Times on Each Machine",
      "doi": "10.3390/math7030301",
      "openalex_id": "W2922957460",
      "year": 2019,
      "cited_by_count": 9,
      "source": "openalex"
    },
    {
      "title": "Special Issue on Exact and Heuristic Scheduling Algorithms",
      "doi": "10.3390/a13010009",
      "openalex_id": "W2997656693",
      "year": 2019,
      "cited_by_count": 8,
      "source": "openalex"
    },
    {
      "title": "Robust scheduling of EMU first-level maintenance in a stub-end depot under stochastic uncertainties",
      "doi": "10.1016/j.engappai.2023.106398",
      "openalex_id": "W4379046810",
      "year": 2023,
      "cited_by_count": 8,
      "source": "openalex"
    },
    {
      "title": "The single train shortest route problem in a railyard",
      "doi": "10.1007/s11590-021-01761-w",
      "openalex_id": "W3171408142",
      "year": 2021,
      "cited_by_count": 8,
      "source": "openalex"
    },
    {
      "title": "The stage shop scheduling problem: lower bound and metaheuristic",
      "doi": "10.24200/sci.2018.5199.1146",
      "openalex_id": "W2913074586",
      "year": 2018,
      "cited_by_count": 8,
      "source": "openalex"
    },
    {
      "title": "A comparative study on three graph-based constructive algorithms for multi-stage scheduling with blocking",
      "doi": "10.3934/jimo.2018040",
      "openalex_id": "W2802307620",
      "year": 2018,
      "cited_by_count": 6,
      "source": "openalex"
    },
    {
      "title": "Scheduling for multi-robot routing with blocking and enabling constraints",
      "doi": "10.1007/s10951-021-00684-9",
      "openalex_id": "W3159406747",
      "year": 2021,
      "cited_by_count": 6,
      "source": "openalex"
    },
    {
      "title": "The shunting scheduling of EMU first-level maintenance in a stub-end depot",
      "doi": "10.1007/s10696-022-09459-6",
      "openalex_id": "W4289261611",
      "year": 2022,
      "cited_by_count": 6,
      "source": "openalex"
    },
    {
      "title": "Freight railcar-to-train assignment and departure scheduling in a railyard",
      "doi": "10.1016/j.ejor.2023.11.006",
      "openalex_id": "W4388448331",
      "year": 2023,
      "cited_by_count": 5,
      "source": "openalex"
    },
    {
      "title": "Truck scheduling in tank terminals",
      "doi": "10.1016/j.ejtl.2020.100001",
      "openalex_id": "W3028506544",
      "year": 2020,
      "cited_by_count": 5,
      "source": "openalex"
    },
    {
      "title": "A Permutation-Based Neighborhood for the Blocking Job-Shop Problem with Total Tardiness Minimization",
      "doi": "10.1007/978-3-319-89920-6_77",
      "openalex_id": "W2804942412",
      "year": 2018,
      "cited_by_count": 4,
      "source": "openalex"
    },
    {
      "title": "A Real-World Transport Scheduler Applied to Australian Sugarcane Industry",
      "doi": "10.1109/itsc45102.2020.9294635",
      "openalex_id": "W3086822092",
      "year": 2020,
      "cited_by_count": 4,
      "source": "openalex"
    },
    {
      "title": "Collaborative Optimization of Car-flow Organization for Freight Trains Based on Adjacent Technical Stations",
      "doi": "10.7307/ptt.v33i1.3601",
      "openalex_id": "W3126658864",
      "year": 2021,
      "cited_by_count": 4,
      "source": "openalex"
    },
    {
      "title": "Solving rescheduling problems in heterogeneous urban railway networks using hybrid quantum–classical approach",
      "doi": "10.1016/j.jrtpm.2025.100521",
      "openalex_id": "W4410457091",
      "year": 2025,
      "cited_by_count": 4,
      "source": "openalex"
    },
    {
      "title": "Evaluation of VaR and CVaR for the makespan in interval valued blocking job shops",
      "doi": "10.1016/j.ijpe.2022.108455",
      "openalex_id": "W4212764592",
      "year": 2022,
      "cited_by_count": 4,
      "source": "openalex"
    },
    {
      "title": "Quadratic and Higher-Order Unconstrained Binary Optimization of Railway Dispatching Problem for Quantum Computing",
      "doi": null,
      "openalex_id": "W3181006107",
      "year": 2021,
      "cited_by_count": 3,
      "source": "openalex"
    },
    {
      "title": "Discrete Optimization on Train Rescheduling on Single-Track Railway: Clustering Hierarchy and Heuristic Search",
      "doi": "10.1155/2020/8892372",
      "openalex_id": "W3108500205",
      "year": 2020,
      "cited_by_count": 3,
      "source": "openalex"
    },
    {
      "title": "Quantum Annealing in the NISQ Era: Railway Conflict Management",
      "doi": "10.3390/e25020191",
      "openalex_id": "W4200629338",
      "year": 2023,
      "cited_by_count": 3,
      "source": "openalex"
    },
    {
      "title": "A Tree neural network deep reinforcement learning for flexible job shop scheduling with transportation constraints",
      "doi": "10.1016/j.swevo.2025.102102",
      "openalex_id": "W4412704535",
      "year": 2025,
      "cited_by_count": 3,
      "source": "openalex"
    },
    {
      "title": "A Dynamic Approach to Selecting Time Points for Short-Term Scheduling with Application to Multipurpose Facilities",
      "doi": "10.1021/acs.iecr.0c00472",
      "openalex_id": "W3017148266",
      "year": 2020,
      "cited_by_count": 3,
      "source": "openalex"
    },
    {
      "title": "A MILP model to minimize total tardiness in a job shop scheduling problem with blocking and no-wait constraints",
      "doi": "10.1051/ro/2025109",
      "openalex_id": "W4412721815",
      "year": 2025,
      "cited_by_count": 2,
      "source": "openalex"
    },
    {
      "title": "Blocking Cyclic Job-Shop Scheduling Problems",
      "doi": "10.3390/a15100375",
      "openalex_id": "W4306362410",
      "year": 2022,
      "cited_by_count": 2,
      "source": "openalex"
    },
    {
      "title": "Solving train scheduling problems as a job shop: A brief review",
      "doi": "10.17352/amp.000058",
      "openalex_id": "W4309731589",
      "year": 2022,
      "cited_by_count": 1,
      "source": "openalex"
    },
    {
      "title": "High-speed train scheduling and rescheduling models",
      "doi": "10.1109/sose50414.2020.9130554",
      "openalex_id": "W3039384547",
      "year": 2020,
      "cited_by_count": 1,
      "source": "openalex"
    },
    {
      "title": "An Improved Adaptive Particle Swarm Optimization Method for High-speed Train Scheduling in Unexpected Events",
      "doi": "10.1109/icca54724.2022.9831865",
      "openalex_id": "W4287846158",
      "year": 2022,
      "cited_by_count": 1,
      "source": "openalex"
    },
    {
      "title": "An improved ant colony optimization strategy for dual-objective high-speed train scheduling",
      "doi": "10.1007/s44443-025-00226-9",
      "openalex_id": "W4413402269",
      "year": 2025,
      "cited_by_count": 1,
      "source": "openalex"
    },
    {
      "title": "Comparative Study and Hybrid Modeling of Vehicle Routing Problem and Job Shop Scheduling Problem",
      "doi": "10.1007/978-981-15-3588-8_35",
      "openalex_id": "W3020835354",
      "year": 2020,
      "cited_by_count": 1,
      "source": "openalex"
    },
    {
      "title": "Preface",
      "doi": "10.1007/s10951-018-0557-1",
      "openalex_id": "W4251161156",
      "year": 2018,
      "cited_by_count": 0,
      "source": "openalex"
    },
    {
      "title": "The Estimation Distribution Algorithm for the Blocking Job Shop Scheduling Problem",
      "doi": "10.3390/app15179339",
      "openalex_id": "W4413619169",
      "year": 2025,
      "cited_by_count": 0,
      "source": "openalex"
    },
    {
      "title": "AVALIAÇÃO DE CAPACIDADE EM PÁTIOS FERROVIÁRIOS PLANOS DE CLASSIFICACÃO ATRAVÉS DE MODELO DE OTIMIZACÃO",
      "doi": "10.59254/sbpo-2020-122624",
      "openalex_id": "W4390627109",
      "year": 2020,
      "cited_by_count": 0,
      "source": "openalex"
    },
    {
      "title": "AVALIAÇÃO DE CAPACIDADE DE PROCESSAMENTO EM PÁTIOS FERROVIÁRIOS PLANOS DE CLASSIFICAÇÃO ATRAVÉS DE MODELO DE OTIMIZAÇÃO",
      "doi": "10.17771/pucrio.acad.55724",
      "openalex_id": "W4207016596",
      "year": 2021,
      "cited_by_count": 0,
      "source": "openalex"
    },
    {
      "title": "Tren Çizelgeleme Problemine Karmaşık Atölye Tabanlı Bir Yaklaşım: Türkiye Uygulama Örnekleri",
      "doi": "10.47072/demiryolu.1841796",
      "openalex_id": "W7125174659",
      "year": 2026,
      "cited_by_count": 0,
      "source": "openalex"
    },
    {
      "title": "Multiple Train Repositioning Operations in a Railyard Network",
      "doi": "10.1007/s43069-022-00171-7",
      "openalex_id": "W4306167533",
      "year": 2022,
      "cited_by_count": 0,
      "source": "openalex"
    },
    {
      "title": "Optimization and Model Predictive Control for Coordinated Multi-Train Systems with Virtual Block Constraints",
      "doi": "10.2139/ssrn.6467403",
      "openalex_id": "W7140284135",
      "year": 2026,
      "cited_by_count": 0,
      "source": "openalex"
    },
    {
      "title": "Application of Model-Checking Techniques to Railway Scheduling Problems",
      "doi": "10.1007/978-3-032-12484-5_12",
      "openalex_id": "W7127965385",
      "year": 2026,
      "cited_by_count": 0,
      "source": "openalex"
    }
  ],
  "references_count": 37,
  "cited_by_count": 49,
  "formulas": []
}
