{
  "schema_version": "dossier-1",
  "source": {
    "title": "Modeling railway disruption lengths with Copula Bayesian Networks",
    "doi": "10.1016/j.trc.2016.04.018",
    "arxiv_id": null,
    "openalex_id": "W2342408036",
    "authors": [
      "A.A. Zilko",
      "Dorota Kurowicka",
      "Rob M.P. Goverde"
    ],
    "year": 2016,
    "venue": "Transportation Research Part C Emerging Technologies",
    "publisher": "Elsevier BV",
    "cited_by_count": 94,
    "scopus_cited_by_count": 96,
    "api": "openalex+elsevier",
    "retrieved": "2026-06-21",
    "file_path": null,
    "file_sha256": "33fc37e21f6416483317401440584332c2d395bea41b36bb670e8a912c7db7f2",
    "entitlement": "tud-subscription",
    "landing_url": "https://doi.org/10.1016/j.trc.2016.04.018"
  },
  "references": [
    {
      "title": "A new look at the statistical model identification",
      "doi": "10.1109/tac.1974.1100705",
      "openalex_id": "W2142635246",
      "year": 1974,
      "cited_by_count": 50701,
      "source": "openalex"
    },
    {
      "title": "Elements of Information Theory",
      "doi": "10.1002/0471200611",
      "openalex_id": "W2099111195",
      "year": 2001,
      "cited_by_count": 37913,
      "source": "openalex"
    },
    {
      "title": "Naive Bayesian Classifier for Rapid Assignment of rRNA Sequences into the New Bacterial Taxonomy",
      "doi": "10.1128/aem.00062-07",
      "openalex_id": "W2152885278",
      "year": 2007,
      "cited_by_count": 20485,
      "source": "openalex"
    },
    {
      "title": "Elements of Information Theory",
      "doi": "10.1002/047174882x",
      "openalex_id": "W2478708596",
      "year": 2005,
      "cited_by_count": 12974,
      "source": "openalex"
    },
    {
      "title": "Fonctions de répartition à N dimensions et leurs marges",
      "doi": null,
      "openalex_id": "W2907233437",
      "year": 1959,
      "cited_by_count": 4297,
      "source": "openalex"
    },
    {
      "title": "Asymptotic Theory of Certain \"Goodness of Fit\" Criteria Based on Stochastic Processes",
      "doi": "10.1214/aoms/1177729437",
      "openalex_id": "W1973429805",
      "year": 1952,
      "cited_by_count": 3536,
      "source": "openalex"
    },
    {
      "title": "Remarks on a Multivariate Transformation",
      "doi": "10.1214/aoms/1177729394",
      "openalex_id": "W1995565517",
      "year": 1952,
      "cited_by_count": 2856,
      "source": "openalex"
    },
    {
      "title": "Learning Bayesian Networks with the<b>bnlearn</b><i>R</i>Package",
      "doi": "10.18637/jss.v035.i03",
      "openalex_id": "W2128088446",
      "year": 2010,
      "cited_by_count": 1722,
      "source": "openalex"
    },
    {
      "title": "An overview of recovery models and algorithms for real-time railway rescheduling",
      "doi": "10.1016/j.trb.2014.01.009",
      "openalex_id": "W2134131633",
      "year": 2014,
      "cited_by_count": 662,
      "source": "openalex"
    },
    {
      "title": "On the Distribution of the Two-Sample Cramer-von Mises Criterion",
      "doi": "10.1214/aoms/1177704477",
      "openalex_id": "W2121360982",
      "year": 1962,
      "cited_by_count": 603,
      "source": "openalex"
    },
    {
      "title": "Goodness-of-fit tests on a circle. II",
      "doi": "10.1093/biomet/49.1-2.57",
      "openalex_id": "W2165261674",
      "year": 1962,
      "cited_by_count": 405,
      "source": "openalex"
    },
    {
      "title": "Dependence Structures for Multivariate High-Frequency Data in Finance",
      "doi": null,
      "openalex_id": "W2529733609",
      "year": 2002,
      "cited_by_count": 389,
      "source": "openalex"
    },
    {
      "title": "Goodness-of-fit tests on a circle",
      "doi": "10.1093/biomet/48.1-2.109",
      "openalex_id": "W4248568024",
      "year": 1961,
      "cited_by_count": 371,
      "source": "openalex"
    },
    {
      "title": "An exploratory hazard-based analysis of highway incident duration",
      "doi": "10.1016/s0965-8564(98)00065-2",
      "openalex_id": "W1995840715",
      "year": 2000,
      "cited_by_count": 324,
      "source": "openalex"
    },
    {
      "title": "Dependence structures for multivariate high-frequency data in finance",
      "doi": "10.1080/713666155",
      "openalex_id": "W2133509827",
      "year": 2003,
      "cited_by_count": 317,
      "source": "openalex"
    },
    {
      "title": "Learning Bayesian Network Model Structure from Data",
      "doi": null,
      "openalex_id": "W2146521249",
      "year": 2003,
      "cited_by_count": 294,
      "source": "openalex"
    },
    {
      "title": "Railway Operation and Control",
      "doi": null,
      "openalex_id": "W82907418",
      "year": 2002,
      "cited_by_count": 253,
      "source": "openalex"
    },
    {
      "title": "Molecular Similarity Searching Using Atom Environments, Information-Based Feature Selection, and a Naïve Bayesian Classifier",
      "doi": "10.1021/ci034207y",
      "openalex_id": "W1983610905",
      "year": 2003,
      "cited_by_count": 248,
      "source": "openalex"
    },
    {
      "title": "Incident characteristics, frequency, and duration on a high volume urban freeway",
      "doi": "10.1016/0191-2607(89)90086-1",
      "openalex_id": "W2010039425",
      "year": 1989,
      "cited_by_count": 244,
      "source": "openalex"
    },
    {
      "title": "Hybrid Method for Quantifying and Analyzing Bayesian Belief Nets",
      "doi": "10.1002/qre.808",
      "openalex_id": "W2009403078",
      "year": 2006,
      "cited_by_count": 146,
      "source": "openalex"
    },
    {
      "title": "DISTRIBUTION-FREE CONTINUOUS BAYESIAN BELIEF NETS",
      "doi": "10.1142/9789812703378_0022",
      "openalex_id": "W2483464204",
      "year": 2005,
      "cited_by_count": 124,
      "source": "openalex"
    },
    {
      "title": "Black spots identification through a Bayesian Networks quantification of accident risk index",
      "doi": "10.1016/j.trc.2012.12.008",
      "openalex_id": "W1987342238",
      "year": 2013,
      "cited_by_count": 115,
      "source": "openalex"
    },
    {
      "title": "New Model for Predicting Freeway Incidents and Incident Delays",
      "doi": "10.1061/(asce)0733-947x(1997)123:4(267)",
      "openalex_id": "W2088796177",
      "year": 1997,
      "cited_by_count": 109,
      "source": "openalex"
    },
    {
      "title": "Power studies of some tests for uniformity",
      "doi": "10.1080/00949657708810150",
      "openalex_id": "W2128140823",
      "year": 1977,
      "cited_by_count": 88,
      "source": "openalex"
    },
    {
      "title": "Comparison of a Bayesian classifier with a multilayer feed-forward neural network using the example of plant/weed/soil discrimination",
      "doi": "10.1016/s0168-1699(02)00223-5",
      "openalex_id": "W2026765215",
      "year": 2003,
      "cited_by_count": 84,
      "source": "openalex"
    },
    {
      "title": "Mining and visualising ordinal data with non-parametric continuous BBNs",
      "doi": "10.1016/j.csda.2008.09.032",
      "openalex_id": "W2002551239",
      "year": 2008,
      "cited_by_count": 72,
      "source": "openalex"
    },
    {
      "title": "Effectiveness of dynamic reordering and rerouting of trains in a complicated and densely occupied station area",
      "doi": "10.1080/03081060.2011.577152",
      "openalex_id": "W1988496544",
      "year": 2011,
      "cited_by_count": 67,
      "source": "openalex"
    },
    {
      "title": "Multivariate Simulation and Multimodal Dependence Modeling of Vehicle Axle Weights with Copulas",
      "doi": "10.1061/(asce)0733-947x(2006)132:12(945)",
      "openalex_id": "W1972518832",
      "year": 2006,
      "cited_by_count": 35,
      "source": "openalex"
    },
    {
      "title": "Combined use of sensor data and structural knowledge processed by Bayesian network: Application to a railway diagnosis aid scheme",
      "doi": "10.1016/j.trc.2008.04.001",
      "openalex_id": "W2069786353",
      "year": 2008,
      "cited_by_count": 35,
      "source": "openalex"
    },
    {
      "title": "Bayesian network-based formulation and analysis for toll road utilization supported by traffic information provision",
      "doi": "10.1016/j.trc.2015.09.005",
      "openalex_id": "W1846810705",
      "year": 2015,
      "cited_by_count": 31,
      "source": "openalex"
    },
    {
      "title": "Copula in a multivariate mixed discrete–continuous model",
      "doi": "10.1016/j.csda.2016.02.017",
      "openalex_id": "W2345371731",
      "year": 2016,
      "cited_by_count": 30,
      "source": "openalex"
    },
    {
      "title": "Regional Air Quality Conformity in Transportation Networks with Stochastic Dependencies: A Theoretical Copula-Based Model",
      "doi": "10.1007/s11067-013-9185-7",
      "openalex_id": "W2062844300",
      "year": 2013,
      "cited_by_count": 19,
      "source": "openalex"
    },
    {
      "title": "Non-Parametric Bayesian Network to Forecast Railway Disruption Lengths",
      "doi": "10.4203/ccp.104.99",
      "openalex_id": "W3184649292",
      "year": 2014,
      "cited_by_count": 6,
      "source": "openalex"
    },
    {
      "title": "The Copula Bayesian Network with mixed discrete and continuous nodes to forecast railway disruption lengths",
      "doi": null,
      "openalex_id": "W1914097481",
      "year": 2015,
      "cited_by_count": 5,
      "source": "openalex"
    },
    {
      "title": "Assessment of Stochastic Capacity Consumption in Railway Networks",
      "doi": null,
      "openalex_id": "W2595020851",
      "year": 2015,
      "cited_by_count": 5,
      "source": "openalex"
    },
    {
      "title": "Review of railway disruption management practice and literature",
      "doi": null,
      "openalex_id": "W2107170266",
      "year": 2015,
      "cited_by_count": 4,
      "source": "openalex"
    }
  ],
  "cited_by": [
    {
      "title": "Resilience in railway transport systems: a literature review and research agenda",
      "doi": "10.1080/01441647.2020.1728419",
      "openalex_id": "W3005537099",
      "year": 2020,
      "cited_by_count": 366,
      "source": "openalex"
    },
    {
      "title": "Recent applications of big data analytics in railway transportation systems: A survey",
      "doi": "10.1016/j.trc.2018.03.010",
      "openalex_id": "W2794204271",
      "year": 2018,
      "cited_by_count": 313,
      "source": "openalex"
    },
    {
      "title": "A literature review of Artificial Intelligence applications in railway systems",
      "doi": "10.1016/j.trc.2022.103679",
      "openalex_id": "W4229007983",
      "year": 2022,
      "cited_by_count": 296,
      "source": "openalex"
    },
    {
      "title": "Railway timetable rescheduling with flexible stopping and flexible short-turning during disruptions",
      "doi": "10.1016/j.trb.2019.02.015",
      "openalex_id": "W2935336332",
      "year": 2019,
      "cited_by_count": 159,
      "source": "openalex"
    },
    {
      "title": "Artificial Intelligence in Railway Transport: Taxonomy, Regulations, and Applications",
      "doi": "10.1109/tits.2021.3131637",
      "openalex_id": "W3216409334",
      "year": 2021,
      "cited_by_count": 115,
      "source": "openalex"
    },
    {
      "title": "Modeling train operation as sequences: A study of delay prediction with operation and weather data",
      "doi": "10.1016/j.tre.2020.102022",
      "openalex_id": "W3044811479",
      "year": 2020,
      "cited_by_count": 99,
      "source": "openalex"
    },
    {
      "title": "Railway dangerous goods transportation system risk analysis: An Interpretive Structural Modeling and Bayesian Network combining approach",
      "doi": "10.1016/j.ress.2020.107220",
      "openalex_id": "W3082981368",
      "year": 2020,
      "cited_by_count": 92,
      "source": "openalex"
    },
    {
      "title": "Copula-based Bayesian network model for process system risk assessment",
      "doi": "10.1016/j.psep.2019.01.022",
      "openalex_id": "W2913264880",
      "year": 2019,
      "cited_by_count": 84,
      "source": "openalex"
    },
    {
      "title": "Early warning of water quality degradation: A copula-based Bayesian network model for highly efficient water quality risk assessment",
      "doi": "10.1016/j.jenvman.2021.112749",
      "openalex_id": "W3160154289",
      "year": 2021,
      "cited_by_count": 78,
      "source": "openalex"
    },
    {
      "title": "Macroscopic multiple-station short-turning model in case of complete railway blockages",
      "doi": "10.1016/j.trc.2018.02.006",
      "openalex_id": "W2792839095",
      "year": 2018,
      "cited_by_count": 73,
      "source": "openalex"
    },
    {
      "title": "Multi-level condition-based maintenance planning for railway infrastructures – A scenario-based chance-constrained approach",
      "doi": "10.1016/j.trc.2017.08.018",
      "openalex_id": "W2752669015",
      "year": 2017,
      "cited_by_count": 71,
      "source": "openalex"
    },
    {
      "title": "Train Dispatching Management With Data- Driven Approaches: A Comprehensive Review and Appraisal",
      "doi": "10.1109/access.2019.2935106",
      "openalex_id": "W2969003068",
      "year": 2019,
      "cited_by_count": 69,
      "source": "openalex"
    },
    {
      "title": "A Bayesian network model to predict the effects of interruptions on train operations",
      "doi": "10.1016/j.trc.2020.02.021",
      "openalex_id": "W3008790764",
      "year": 2020,
      "cited_by_count": 69,
      "source": "openalex"
    },
    {
      "title": "Railway disruption management challenges and possible solution directions",
      "doi": "10.1007/s12469-017-0157-z",
      "openalex_id": "W2596867035",
      "year": 2017,
      "cited_by_count": 68,
      "source": "openalex"
    },
    {
      "title": "A review of train delay prediction approaches",
      "doi": "10.1016/j.jrtpm.2022.100312",
      "openalex_id": "W4220694402",
      "year": 2022,
      "cited_by_count": 67,
      "source": "openalex"
    },
    {
      "title": "A predictive model of train delays on a railway line",
      "doi": "10.1002/for.2639",
      "openalex_id": "W2994808218",
      "year": 2019,
      "cited_by_count": 67,
      "source": "openalex"
    },
    {
      "title": "A microscopic model for optimal train short-turnings during complete blockages",
      "doi": "10.1016/j.trb.2017.10.002",
      "openalex_id": "W2761479005",
      "year": 2017,
      "cited_by_count": 65,
      "source": "openalex"
    },
    {
      "title": "Metro disruption management: Optimal initiation time of substitute bus services under uncertain system recovery time",
      "doi": "10.1016/j.trc.2018.11.001",
      "openalex_id": "W2900757585",
      "year": 2018,
      "cited_by_count": 60,
      "source": "openalex"
    },
    {
      "title": "A combined physics of failure and Bayesian network reliability analysis method for complex electronic systems",
      "doi": "10.1016/j.psep.2021.01.023",
      "openalex_id": "W3126782061",
      "year": 2021,
      "cited_by_count": 59,
      "source": "openalex"
    },
    {
      "title": "Impact of railway disruption predictions and rescheduling on passenger delays",
      "doi": "10.1016/j.jrtpm.2018.02.002",
      "openalex_id": "W2800900810",
      "year": 2018,
      "cited_by_count": 57,
      "source": "openalex"
    },
    {
      "title": "A hybrid model to improve the train running time prediction ability during high-speed railway disruptions",
      "doi": "10.1016/j.ssci.2019.104510",
      "openalex_id": "W2981207057",
      "year": 2019,
      "cited_by_count": 56,
      "source": "openalex"
    },
    {
      "title": "Handling uncertainty in train timetable rescheduling: A review of the literature and future research directions",
      "doi": "10.1016/j.tre.2024.103429",
      "openalex_id": "W4391418544",
      "year": 2024,
      "cited_by_count": 56,
      "source": "openalex"
    },
    {
      "title": "A fuzzy rough copula Bayesian network model for solving complex hospital service quality assessment",
      "doi": "10.1007/s40747-023-01002-w",
      "openalex_id": "W4360869630",
      "year": 2023,
      "cited_by_count": 53,
      "source": "openalex"
    },
    {
      "title": "Near-term train delay prediction in the Dutch railways network",
      "doi": "10.1080/23248378.2020.1843194",
      "openalex_id": "W3103044453",
      "year": 2020,
      "cited_by_count": 52,
      "source": "openalex"
    },
    {
      "title": "Metro system disruption management and substitute bus service: a systematic review and future directions",
      "doi": "10.1080/01441647.2020.1834468",
      "openalex_id": "W3094256243",
      "year": 2020,
      "cited_by_count": 51,
      "source": "openalex"
    },
    {
      "title": "Modeling train timetables as images: A cost-sensitive deep learning framework for delay propagation pattern recognition",
      "doi": "10.1016/j.eswa.2021.114996",
      "openalex_id": "W3145694833",
      "year": 2021,
      "cited_by_count": 51,
      "source": "openalex"
    },
    {
      "title": "A delay root cause discovery and timetable adjustment model for enhancing the punctuality of railway services",
      "doi": "10.1016/j.trc.2016.10.009",
      "openalex_id": "W2542154306",
      "year": 2016,
      "cited_by_count": 48,
      "source": "openalex"
    },
    {
      "title": "Dynamic and robust timetable rescheduling for uncertain railway disruptions",
      "doi": "10.1016/j.jrtpm.2020.100196",
      "openalex_id": "W3015526660",
      "year": 2020,
      "cited_by_count": 48,
      "source": "openalex"
    },
    {
      "title": "A scalable fuzzy support vector machine for fault detection in transportation systems",
      "doi": "10.1016/j.eswa.2018.02.017",
      "openalex_id": "W2791280689",
      "year": 2018,
      "cited_by_count": 48,
      "source": "openalex"
    },
    {
      "title": "Enhancing the Understanding of Train Delays With Delay Evolution Pattern Discovery: A Clustering and Bayesian Network Approach",
      "doi": "10.1109/tits.2022.3140386",
      "openalex_id": "W4206338598",
      "year": 2022,
      "cited_by_count": 48,
      "source": "openalex"
    },
    {
      "title": "Dynamic railway timetable rescheduling for multiple connected disruptions",
      "doi": "10.1016/j.trc.2021.103080",
      "openalex_id": "W3133632639",
      "year": 2021,
      "cited_by_count": 45,
      "source": "openalex"
    },
    {
      "title": "Knowledge representation using non-parametric Bayesian networks for tunneling risk analysis",
      "doi": "10.1016/j.ress.2019.106529",
      "openalex_id": "W2947403397",
      "year": 2019,
      "cited_by_count": 44,
      "source": "openalex"
    },
    {
      "title": "First train timetabling and bus service bridging in intermodal bus-and-train transit networks",
      "doi": "10.1016/j.trb.2021.05.011",
      "openalex_id": "W3172053772",
      "year": 2021,
      "cited_by_count": 42,
      "source": "openalex"
    },
    {
      "title": "An adaptive decision making method with copula Bayesian network for location selection",
      "doi": "10.1016/j.ins.2020.07.063",
      "openalex_id": "W3045973712",
      "year": 2020,
      "cited_by_count": 41,
      "source": "openalex"
    },
    {
      "title": "Statistical evaluation of data requirement for ramp metering performance assessment",
      "doi": "10.1016/j.tra.2020.09.011",
      "openalex_id": "W3091804291",
      "year": 2020,
      "cited_by_count": 36,
      "source": "openalex"
    },
    {
      "title": "A Copula-Bayesian approach for risk assessment of decommissioning operation of aging subsea pipelines",
      "doi": "10.1016/j.psep.2022.09.019",
      "openalex_id": "W4295529413",
      "year": 2022,
      "cited_by_count": 35,
      "source": "openalex"
    },
    {
      "title": "Prediction of train arrival delays considering route conflicts at multi-line stations",
      "doi": "10.1016/j.trc.2022.103606",
      "openalex_id": "W4214820798",
      "year": 2022,
      "cited_by_count": 35,
      "source": "openalex"
    },
    {
      "title": "Analyzing network-wide patterns of rail transit delays using Bayesian network learning",
      "doi": "10.1016/j.trc.2020.102749",
      "openalex_id": "W3080329174",
      "year": 2020,
      "cited_by_count": 35,
      "source": "openalex"
    },
    {
      "title": "Analysis of train derailment severity using vine copula quantile regression modeling",
      "doi": "10.1016/j.trc.2019.06.015",
      "openalex_id": "W2955528016",
      "year": 2019,
      "cited_by_count": 32,
      "source": "openalex"
    },
    {
      "title": "Identifying the rail operating features associated to intermodal freight rail operation delays",
      "doi": "10.1016/j.trc.2022.103993",
      "openalex_id": "W4312203572",
      "year": 2022,
      "cited_by_count": 32,
      "source": "openalex"
    },
    {
      "title": "Timetable Recovery After Disturbances in Metro Operations: An Exact and Efficient Solution",
      "doi": "10.1109/tits.2020.3041151",
      "openalex_id": "W3110768411",
      "year": 2020,
      "cited_by_count": 30,
      "source": "openalex"
    },
    {
      "title": "Explainable train delay propagation: A graph attention network approach",
      "doi": "10.1016/j.tre.2024.103457",
      "openalex_id": "W4392337929",
      "year": 2024,
      "cited_by_count": 27,
      "source": "openalex"
    },
    {
      "title": "Train rescheduling in a major disruption on a high-speed railway network with seat reservation",
      "doi": "10.1080/23249935.2021.1877369",
      "openalex_id": "W3122713441",
      "year": 2021,
      "cited_by_count": 26,
      "source": "openalex"
    },
    {
      "title": "A data-driven approach for quantifying the resilience of railway networks",
      "doi": "10.1016/j.tra.2023.103913",
      "openalex_id": "W4388966951",
      "year": 2023,
      "cited_by_count": 25,
      "source": "openalex"
    },
    {
      "title": "On the dynamic vulnerability of an urban rail transit system and the impact of human mobility",
      "doi": "10.1016/j.jtrangeo.2024.103850",
      "openalex_id": "W4393356347",
      "year": 2024,
      "cited_by_count": 24,
      "source": "openalex"
    },
    {
      "title": "Optimizing Disruption Tolerance for Rail Transit Networks Under Uncertainty",
      "doi": "10.1287/trsc.2021.1040",
      "openalex_id": "W3188287337",
      "year": 2021,
      "cited_by_count": 24,
      "source": "openalex"
    },
    {
      "title": "Train traffic control in merging stations: A data-driven approach",
      "doi": "10.1016/j.trc.2023.104155",
      "openalex_id": "W4375857352",
      "year": 2023,
      "cited_by_count": 21,
      "source": "openalex"
    },
    {
      "title": "Railway network delay evolution: A heterogeneous graph neural network approach",
      "doi": "10.1016/j.asoc.2024.111640",
      "openalex_id": "W4394987665",
      "year": 2024,
      "cited_by_count": 20,
      "source": "openalex"
    },
    {
      "title": "Modeling tamping recovery of track geometry using the copula-based approach",
      "doi": "10.1177/0954409718757556",
      "openalex_id": "W2793346253",
      "year": 2018,
      "cited_by_count": 19,
      "source": "openalex"
    },
    {
      "title": "Short-Term Arrival Delay Time Prediction in Freight Rail Operations Using Data-Driven Models",
      "doi": "10.1109/access.2023.3275022",
      "openalex_id": "W4382296615",
      "year": 2023,
      "cited_by_count": 16,
      "source": "openalex"
    },
    {
      "title": "A Nonparametric Bayesian Network Model for Predicting Corrosion Depth on Buried Pipelines",
      "doi": "10.5006/3421",
      "openalex_id": "W2999480807",
      "year": 2020,
      "cited_by_count": 16,
      "source": "openalex"
    },
    {
      "title": "Quantifying the cascading effects of passenger delays",
      "doi": "10.1016/j.ress.2021.107629",
      "openalex_id": "W3137317588",
      "year": 2021,
      "cited_by_count": 14,
      "source": "openalex"
    },
    {
      "title": "An estimation framework to quantify railway disruption parameters",
      "doi": "10.1049/itr2.12095",
      "openalex_id": "W3177723759",
      "year": 2021,
      "cited_by_count": 13,
      "source": "openalex"
    },
    {
      "title": "A copula‐based method of risk prediction for autonomous underwater gliders in dynamic environments",
      "doi": "10.1111/risa.14149",
      "openalex_id": "W4367318610",
      "year": 2023,
      "cited_by_count": 12,
      "source": "openalex"
    },
    {
      "title": "A Global Modeling Pruning Ensemble Stacking With Deep Learning and Neural Network Meta-Learner for Passenger Train Delay Prediction",
      "doi": "10.1109/access.2023.3287975",
      "openalex_id": "W4381327697",
      "year": 2023,
      "cited_by_count": 12,
      "source": "openalex"
    },
    {
      "title": "An integrated framework for assessing service efficiency and stability of rail transit systems",
      "doi": "10.1016/j.trc.2017.03.006",
      "openalex_id": "W2597363362",
      "year": 2017,
      "cited_by_count": 11,
      "source": "openalex"
    },
    {
      "title": "Statistical model for determining the quality of cargo work JSC “Uzbekistan Railways”",
      "doi": "10.1051/e3sconf/202340206016",
      "openalex_id": "W4385671918",
      "year": 2023,
      "cited_by_count": 10,
      "source": "openalex"
    },
    {
      "title": "Prediction of departure delays at original stations using deep learning approaches: A combination of route conflicts and rolling stock connections",
      "doi": "10.1016/j.eswa.2023.120500",
      "openalex_id": "W4377100944",
      "year": 2023,
      "cited_by_count": 9,
      "source": "openalex"
    },
    {
      "title": "A Max–Min Fairness-Inspired Approach to Enhance the Performance of Multimodal Transportation Networks",
      "doi": "10.3390/su16124914",
      "openalex_id": "W4399429073",
      "year": 2024,
      "cited_by_count": 8,
      "source": "openalex"
    },
    {
      "title": "Entropy and the Kullback–Leibler Divergence for Bayesian Networks: Computational Complexity and Efficient Implementation",
      "doi": "10.3390/a17010024",
      "openalex_id": "W4390669614",
      "year": 2024,
      "cited_by_count": 8,
      "source": "openalex"
    },
    {
      "title": "Train Delay Predictions Using Markov Chains Based on Process Time Deviations and Elastic State Boundaries",
      "doi": "10.3390/math11040839",
      "openalex_id": "W4319595652",
      "year": 2023,
      "cited_by_count": 8,
      "source": "openalex"
    },
    {
      "title": "Two-step optimization of train timetables rescheduling and response vehicles on a disrupted metro line",
      "doi": "10.1016/j.trc.2025.105078",
      "openalex_id": "W4408451225",
      "year": 2025,
      "cited_by_count": 7,
      "source": "openalex"
    },
    {
      "title": "Train driver experience: A big data analysis of learning and retaining the new ERTMS system",
      "doi": "10.1016/j.apergo.2021.103627",
      "openalex_id": "W3211187242",
      "year": 2021,
      "cited_by_count": 7,
      "source": "openalex"
    },
    {
      "title": "Train operation conflict detection for high-speed railways: a naïve Bayes approach",
      "doi": "10.1080/23248378.2022.2071346",
      "openalex_id": "W4229372830",
      "year": 2022,
      "cited_by_count": 7,
      "source": "openalex"
    },
    {
      "title": "A Review of Train Delay Prediction Approaches",
      "doi": "10.2139/ssrn.3964737",
      "openalex_id": "W4244719979",
      "year": 2021,
      "cited_by_count": 7,
      "source": "openalex"
    },
    {
      "title": "A Literature Review On Multimodal Freight Transportation Planning Under Disruptions",
      "doi": "10.1088/1757-899x/337/1/012043",
      "openalex_id": "W2797683863",
      "year": 2018,
      "cited_by_count": 7,
      "source": "openalex"
    },
    {
      "title": "Spatiotemporal Analysis and Risk Prediction of Water Quality Using Copula Bayesian Networks: A Case in Qilu Lake, China",
      "doi": "10.3390/pr12122922",
      "openalex_id": "W4405648501",
      "year": 2024,
      "cited_by_count": 6,
      "source": "openalex"
    },
    {
      "title": "Using Delay Logs and Machine Learning to Support Passenger Railway Operations",
      "doi": "10.1177/03611981221085561",
      "openalex_id": "W4226182767",
      "year": 2022,
      "cited_by_count": 6,
      "source": "openalex"
    },
    {
      "title": "A freight train dispatching approach for handling perturbations: a real case for the longest heavy-haul railway in China",
      "doi": "10.1108/srt-09-2020-0009",
      "openalex_id": "W3108274596",
      "year": 2020,
      "cited_by_count": 6,
      "source": "openalex"
    },
    {
      "title": "KNN-FSVM for Fault Detection in High-Speed Trains",
      "doi": "10.1109/icphm.2018.8448688",
      "openalex_id": "W2889338274",
      "year": 2018,
      "cited_by_count": 6,
      "source": "openalex"
    },
    {
      "title": "Modelling the cascading effects of train delay patterns and inter-train control actions with Bayesian networks",
      "doi": "10.1080/23248378.2023.2194304",
      "openalex_id": "W4362560219",
      "year": 2023,
      "cited_by_count": 4,
      "source": "openalex"
    },
    {
      "title": "A Data-Driven Approach for Quantifying the Resilience of Railway Networks",
      "doi": "10.2139/ssrn.4120071",
      "openalex_id": "W4285150468",
      "year": 2022,
      "cited_by_count": 3,
      "source": "openalex"
    },
    {
      "title": "Multi-reservoirs joint flood control scheduling using a two-layer hedging robust optimization method under uncertain inflows",
      "doi": "10.1016/j.ejrh.2025.102244",
      "openalex_id": "W4407839242",
      "year": 2025,
      "cited_by_count": 2,
      "source": "openalex"
    },
    {
      "title": "Machine Learning: A Basic Overview",
      "doi": "10.1002/9781119229070.ch3",
      "openalex_id": "W4255288744",
      "year": 2017,
      "cited_by_count": 2,
      "source": "openalex"
    },
    {
      "title": "Short-term train arrival delay prediction: a data-driven approach",
      "doi": "10.1108/rs-04-2024-0012",
      "openalex_id": "W4400135943",
      "year": 2024,
      "cited_by_count": 2,
      "source": "openalex"
    },
    {
      "title": "Methodological Approaches to Setting the Goal of Multimodal Transportation Management",
      "doi": "10.1007/978-3-030-57450-5_39",
      "openalex_id": "W3078567028",
      "year": 2020,
      "cited_by_count": 2,
      "source": "openalex"
    },
    {
      "title": "Simulation-Based Method of Capacity Utilization Evaluation to Account for Uncertainty in Recovery Time",
      "doi": "10.1177/0361198118790325",
      "openalex_id": "W2887465697",
      "year": 2018,
      "cited_by_count": 2,
      "source": "openalex"
    },
    {
      "title": "A Disturbance-Driven Textual Model for Train Running Time Prediction on High-Speed Railways",
      "doi": "10.1061/jtepbs.teeng-8389",
      "openalex_id": "W4401401623",
      "year": 2024,
      "cited_by_count": 1,
      "source": "openalex"
    },
    {
      "title": "Integrating graph and neural relational inference for network-wide train delay prediction: An equilibrium between accuracy and interpretability",
      "doi": "10.1016/j.trc.2025.105418",
      "openalex_id": "W4416045003",
      "year": 2025,
      "cited_by_count": 1,
      "source": "openalex"
    },
    {
      "title": "Landing Reliability Assessment of Airdrop System Based on Vine-Bayesian Network",
      "doi": "10.1155/2023/1773841",
      "openalex_id": "W4367366190",
      "year": 2023,
      "cited_by_count": 1,
      "source": "openalex"
    },
    {
      "title": "Inferring failure processes via causality analysis: from event logs to predictive fault trees",
      "doi": "10.1016/j.ress.2026.112242",
      "openalex_id": "W7124601745",
      "year": 2026,
      "cited_by_count": 1,
      "source": "openalex"
    },
    {
      "title": "An Improved Approach Based on Linear Programming Model for Assessing Rail Transit System Resilience under Disruptions",
      "doi": "10.1109/srse56746.2022.10067716",
      "openalex_id": "W4328011127",
      "year": 2022,
      "cited_by_count": 1,
      "source": "openalex"
    },
    {
      "title": "Correlating geometry and tie defects using track automated inspection data",
      "doi": "10.58088/b8p2-8p50",
      "openalex_id": "W2945788047",
      "year": 2024,
      "cited_by_count": 1,
      "source": "openalex"
    },
    {
      "title": "Estimating the Total Delay Times Owing to Disruptions in High-Speed Rail Systems",
      "doi": "10.1109/ictis.2019.8883780",
      "openalex_id": "W2982472914",
      "year": 2019,
      "cited_by_count": 1,
      "source": "openalex"
    },
    {
      "title": "Factors influencing restoration time in railways",
      "doi": "10.1016/j.trip.2024.101268",
      "openalex_id": "W4404235324",
      "year": 2024,
      "cited_by_count": 1,
      "source": "openalex"
    },
    {
      "title": "Feature Selection for Prediction of Railway Disruption Length",
      "doi": "10.1109/itsc.2019.8917030",
      "openalex_id": "W2990371752",
      "year": 2019,
      "cited_by_count": 1,
      "source": "openalex"
    },
    {
      "title": "Probabilistic Fleet Sizing and Routing Problem to Minimize Mobility Disparities",
      "doi": "10.1177/0361198118797829",
      "openalex_id": "W2893551192",
      "year": 2018,
      "cited_by_count": 0,
      "source": "openalex"
    },
    {
      "title": "Reliable Train Delay Forecasting with Conformal Prediction",
      "doi": "10.1007/978-3-032-15120-9_17",
      "openalex_id": "W7127087128",
      "year": 2026,
      "cited_by_count": 0,
      "source": "openalex"
    },
    {
      "title": "Artificial Intelligence in Rail Transit Operations: A Fit-Perspective Review",
      "doi": "10.2139/ssrn.6540152",
      "openalex_id": "W7152010360",
      "year": 2026,
      "cited_by_count": 0,
      "source": "openalex"
    },
    {
      "title": "AI-assisted fibre optic sensing frameworks for automated monitoring of railway infrastructure",
      "doi": "10.1016/j.iintel.2026.100214",
      "openalex_id": "W7162468547",
      "year": 2026,
      "cited_by_count": 0,
      "source": "openalex"
    },
    {
      "title": "Reliability Analysis of Dependent Systems using Copula Bayesian Networks: A Case Study",
      "doi": "10.1088/1757-899x/1043/3/032034",
      "openalex_id": "W3126765911",
      "year": 2021,
      "cited_by_count": 0,
      "source": "openalex"
    },
    {
      "title": "Train rescheduling with consideration of passenger reservicing during severe disruptions",
      "doi": "10.1016/j.jrtpm.2025.100551",
      "openalex_id": "W4414976829",
      "year": 2025,
      "cited_by_count": 0,
      "source": "openalex"
    },
    {
      "title": "A Hybrid CNN+BiLSTM+Attention Model for Improved Train Delay Prediction",
      "doi": "10.1109/icirt66379.2025.11216731",
      "openalex_id": "W4416010947",
      "year": 2025,
      "cited_by_count": 0,
      "source": "openalex"
    },
    {
      "title": "Dependence analysis of social contact behaviors under the impacts of COVID-19 based on a copula approach",
      "doi": "10.1016/j.scitotenv.2023.164437",
      "openalex_id": "W4378603208",
      "year": 2023,
      "cited_by_count": 0,
      "source": "openalex"
    }
  ],
  "references_count": 46,
  "cited_by_count": 94,
  "formulas": [
    {
      "id": "eq-0001",
      "label": "e0005",
      "page_start": null,
      "page_end": null,
      "latex": "\\mathbb{P} \\left(\\right. \\mathit{Group} = i \\left|\\right. 0.975 r_{j} \\leq R \\leq 1.025 r_{j} , T = t_{j} \\left.\\right) = \\frac{\\mathbb{P} \\left(\\right. 0.975 r_{j} \\leq R \\leq 1.025 r_{j} , T = t_{j} \\left|\\right. \\mathit{Group} = i \\left.\\right) \\mathbb{P} \\left(\\mathit{Group} = i\\right)}{\\mathbb{P} \\left(0.975 r_{j} \\leq R \\leq 1.025 r_{j} , T = t_{j}\\right)} .",
      "mathml": "<mml:math xmlns:mml=\"http://www.w3.org/1998/Math/MathML\" xmlns=\"http://www.elsevier.com/xml/ja/dtd\" xmlns:xoe=\"http://www.elsevier.com/xml/xoe/dtd\" xmlns:bk=\"http://www.elsevier.com/xml/bk/dtd\" xmlns:cals=\"http://www.elsevier.com/xml/common/cals/dtd\" xmlns:ce=\"http://www.elsevier.com/xml/common/dtd\" xmlns:ja=\"http://www.elsevier.com/xml/ja/dtd\" xmlns:sa=\"http://www.elsevier.com/xml/common/struct-aff/dtd\" xmlns:sb=\"http://www.elsevier.com/xml/common/struct-bib/dtd\" xmlns:tb=\"http://www.elsevier.com/xml/common/table/dtd\" xmlns:xlink=\"http://www.w3.org/1999/xlink\" xmlns:xocs=\"http://www.elsevier.com/xml/xocs/dtd\" xmlns:dc=\"http://purl.org/dc/elements/1.1/\" xmlns:dcterms=\"http://purl.org/dc/terms/\" xmlns:prism=\"http://prismstandard.org/namespaces/basic/2.0/\" xmlns:xsi=\"http://www.w3.org/2001/XMLSchema-instance\" altimg=\"si79.gif\" overflow=\"scroll\">\n                                    <mml:mrow>\n                                       <mml:mi mathvariant=\"double-struck\">P</mml:mi>\n                                       <mml:mo stretchy=\"false\">(</mml:mo>\n                                       <mml:mi mathvariant=\"italic\">Group</mml:mi>\n                                       <mml:mo>=</mml:mo>\n                                       <mml:mi>i</mml:mi>\n                                       <mml:mo stretchy=\"false\">|</mml:mo>\n                                       <mml:mn>0.975</mml:mn>\n                                       <mml:msub>\n                                          <mml:mrow>\n                                             <mml:mi>r</mml:mi>\n                                          </mml:mrow>\n                                          <mml:mrow>\n                                             <mml:mi>j</mml:mi>\n                                          </mml:mrow>\n                                       </mml:msub>\n                                       <mml:mo>⩽</mml:mo>\n                                       <mml:mi>R</mml:mi>\n                                       <mml:mo>⩽</mml:mo>\n                                       <mml:mn>1.025</mml:mn>\n                                       <mml:msub>\n                                          <mml:mrow>\n                                             <mml:mi>r</mml:mi>\n                                          </mml:mrow>\n                                          <mml:mrow>\n                                             <mml:mi>j</mml:mi>\n                                          </mml:mrow>\n                                       </mml:msub>\n                                       <mml:mtext>,</mml:mtext>\n                                       <mml:mi>T</mml:mi>\n                                       <mml:mo>=</mml:mo>\n                                       <mml:msub>\n                                          <mml:mrow>\n                                             <mml:mi>t</mml:mi>\n                                          </mml:mrow>\n                                          <mml:mrow>\n                                             <mml:mi>j</mml:mi>\n                                          </mml:mrow>\n                                       </mml:msub>\n                                       <mml:mo stretchy=\"false\">)</mml:mo>\n                                       <mml:mo>=</mml:mo>\n                                       <mml:mfrac>\n                                          <mml:mrow>\n                                             <mml:mi mathvariant=\"double-struck\">P</mml:mi>\n                                             <mml:mo stretchy=\"false\">(</mml:mo>\n                                             <mml:mn>0.975</mml:mn>\n                                             <mml:msub>\n                                                <mml:mrow>\n                                                   <mml:mi>r</mml:mi>\n                                                </mml:mrow>\n                                                <mml:mrow>\n                                                   <mml:mi>j</mml:mi>\n                                                </mml:mrow>\n                                             </mml:msub>\n                                             <mml:mo>⩽</mml:mo>\n                                             <mml:mi>R</mml:mi>\n                                             <mml:mo>⩽</mml:mo>\n                                             <mml:mn>1.025</mml:mn>\n                                             <mml:msub>\n                                                <mml:mrow>\n                                                   <mml:mi>r</mml:mi>\n                                                </mml:mrow>\n                                                <mml:mrow>\n                                                   <mml:mi>j</mml:mi>\n                                                </mml:mrow>\n                                             </mml:msub>\n                                             <mml:mtext>,</mml:mtext>\n                                             <mml:mi>T</mml:mi>\n                                             <mml:mo>=</mml:mo>\n                                             <mml:msub>\n                                                <mml:mrow>\n                                                   <mml:mi>t</mml:mi>\n                                                </mml:mrow>\n                                                <mml:mrow>\n                                                   <mml:mi>j</mml:mi>\n                                                </mml:mrow>\n                                             </mml:msub>\n                                             <mml:mo stretchy=\"false\">|</mml:mo>\n                                             <mml:mi mathvariant=\"italic\">Group</mml:mi>\n                                             <mml:mo>=</mml:mo>\n                                             <mml:mi>i</mml:mi>\n                                             <mml:mo stretchy=\"false\">)</mml:mo>\n                                             <mml:mi mathvariant=\"double-struck\">P</mml:mi>\n                                             <mml:mo stretchy=\"false\">(</mml:mo>\n                                             <mml:mi mathvariant=\"italic\">Group</mml:mi>\n                                             <mml:mo>=</mml:mo>\n                                             <mml:mi>i</mml:mi>\n                                             <mml:mo stretchy=\"false\">)</mml:mo>\n                                          </mml:mrow>\n                                          <mml:mrow>\n                                             <mml:mi mathvariant=\"double-struck\">P</mml:mi>\n                                             <mml:mo stretchy=\"false\">(</mml:mo>\n                                             <mml:mn>0.975</mml:mn>\n                                             <mml:msub>\n                                                <mml:mrow>\n                                                   <mml:mi>r</mml:mi>\n                                                </mml:mrow>\n                                                <mml:mrow>\n                                                   <mml:mi>j</mml:mi>\n                                                </mml:mrow>\n                                             </mml:msub>\n                                             <mml:mo>⩽</mml:mo>\n                                             <mml:mi>R</mml:mi>\n                                             <mml:mo>⩽</mml:mo>\n                                             <mml:mn>1.025</mml:mn>\n                                             <mml:msub>\n                                                <mml:mrow>\n                                                   <mml:mi>r</mml:mi>\n                                                </mml:mrow>\n                                                <mml:mrow>\n                                                   <mml:mi>j</mml:mi>\n                                                </mml:mrow>\n                                             </mml:msub>\n                                             <mml:mtext>,</mml:mtext>\n                                             <mml:mi>T</mml:mi>\n                                             <mml:mo>=</mml:mo>\n                                             <mml:msub>\n                                                <mml:mrow>\n                                                   <mml:mi>t</mml:mi>\n                                                </mml:mrow>\n                                                <mml:mrow>\n                                                   <mml:mi>j</mml:mi>\n                                                </mml:mrow>\n                                             </mml:msub>\n                                             <mml:mo stretchy=\"false\">)</mml:mo>\n                                          </mml:mrow>\n                                       </mml:mfrac>\n                                       <mml:mtext>.</mml:mtext>\n                                    </mml:mrow>\n                                 </mml:math>\n                              ",
      "method": "mathml",
      "status": "unreviewed",
      "confidence": null,
      "source_file": null,
      "note": null
    },
    {
      "id": "eq-0002",
      "label": "e0010",
      "page_start": null,
      "page_end": null,
      "latex": "F_{1 , \\ldots , n} \\left(x_{1} , \\ldots , x_{n}\\right) = C \\left(F_{1} \\left(x_{1}\\right) , \\ldots , F_{n} \\left(x_{n}\\right)\\right)",
      "mathml": "<mml:math xmlns:mml=\"http://www.w3.org/1998/Math/MathML\" xmlns=\"http://www.elsevier.com/xml/ja/dtd\" xmlns:xoe=\"http://www.elsevier.com/xml/xoe/dtd\" xmlns:bk=\"http://www.elsevier.com/xml/bk/dtd\" xmlns:cals=\"http://www.elsevier.com/xml/common/cals/dtd\" xmlns:ce=\"http://www.elsevier.com/xml/common/dtd\" xmlns:ja=\"http://www.elsevier.com/xml/ja/dtd\" xmlns:sa=\"http://www.elsevier.com/xml/common/struct-aff/dtd\" xmlns:sb=\"http://www.elsevier.com/xml/common/struct-bib/dtd\" xmlns:tb=\"http://www.elsevier.com/xml/common/table/dtd\" xmlns:xlink=\"http://www.w3.org/1999/xlink\" xmlns:xocs=\"http://www.elsevier.com/xml/xocs/dtd\" xmlns:dc=\"http://purl.org/dc/elements/1.1/\" xmlns:dcterms=\"http://purl.org/dc/terms/\" xmlns:prism=\"http://prismstandard.org/namespaces/basic/2.0/\" xmlns:xsi=\"http://www.w3.org/2001/XMLSchema-instance\" altimg=\"si87.gif\" overflow=\"scroll\">\n                                 <mml:mrow>\n                                    <mml:msub>\n                                       <mml:mrow>\n                                          <mml:mi>F</mml:mi>\n                                       </mml:mrow>\n                                       <mml:mrow>\n                                          <mml:mn>1</mml:mn>\n                                          <mml:mtext>,</mml:mtext>\n                                          <mml:mo>…</mml:mo>\n                                          <mml:mtext>,</mml:mtext>\n                                          <mml:mi>n</mml:mi>\n                                       </mml:mrow>\n                                    </mml:msub>\n                                    <mml:mo stretchy=\"false\">(</mml:mo>\n                                    <mml:msub>\n                                       <mml:mrow>\n                                          <mml:mi>x</mml:mi>\n                                       </mml:mrow>\n                                       <mml:mrow>\n                                          <mml:mn>1</mml:mn>\n                                       </mml:mrow>\n                                    </mml:msub>\n                                    <mml:mtext>,</mml:mtext>\n                                    <mml:mo>…</mml:mo>\n                                    <mml:mtext>,</mml:mtext>\n                                    <mml:msub>\n                                       <mml:mrow>\n                                          <mml:mi>x</mml:mi>\n                                       </mml:mrow>\n                                       <mml:mrow>\n                                          <mml:mi>n</mml:mi>\n                                       </mml:mrow>\n                                    </mml:msub>\n                                    <mml:mo stretchy=\"false\">)</mml:mo>\n                                    <mml:mo>=</mml:mo>\n                                    <mml:mi>C</mml:mi>\n                                    <mml:mo stretchy=\"false\">(</mml:mo>\n                                    <mml:msub>\n                                       <mml:mrow>\n                                          <mml:mi>F</mml:mi>\n                                       </mml:mrow>\n                                       <mml:mrow>\n                                          <mml:mn>1</mml:mn>\n                                       </mml:mrow>\n                                    </mml:msub>\n                                    <mml:mo stretchy=\"false\">(</mml:mo>\n                                    <mml:msub>\n                                       <mml:mrow>\n                                          <mml:mi>x</mml:mi>\n                                       </mml:mrow>\n                                       <mml:mrow>\n                                          <mml:mn>1</mml:mn>\n                                       </mml:mrow>\n                                    </mml:msub>\n                                    <mml:mo stretchy=\"false\">)</mml:mo>\n                                    <mml:mtext>,</mml:mtext>\n                                    <mml:mo>…</mml:mo>\n                                    <mml:mtext>,</mml:mtext>\n                                    <mml:msub>\n                                       <mml:mrow>\n                                          <mml:mi>F</mml:mi>\n                                       </mml:mrow>\n                                       <mml:mrow>\n                                          <mml:mi>n</mml:mi>\n                                       </mml:mrow>\n                                    </mml:msub>\n                                    <mml:mo stretchy=\"false\">(</mml:mo>\n                                    <mml:msub>\n                                       <mml:mrow>\n                                          <mml:mi>x</mml:mi>\n                                       </mml:mrow>\n                                       <mml:mrow>\n                                          <mml:mi>n</mml:mi>\n                                       </mml:mrow>\n                                    </mml:msub>\n                                    <mml:mo stretchy=\"false\">)</mml:mo>\n                                    <mml:mo stretchy=\"false\">)</mml:mo>\n                                 </mml:mrow>\n                              </mml:math>\n                           ",
      "method": "mathml",
      "status": "unreviewed",
      "confidence": null,
      "source_file": null,
      "note": null
    },
    {
      "id": "eq-0003",
      "label": "e0015",
      "page_start": null,
      "page_end": null,
      "latex": "C_{\\Sigma} \\left(u_{1} , \\ldots , u_{n}\\right) = \\Phi_{\\Sigma} \\left(\\Phi^{- 1} \\left(u_{1}\\right) , \\ldots , \\Phi^{- 1} \\left(u_{n}\\right)\\right)",
      "mathml": "<mml:math xmlns:mml=\"http://www.w3.org/1998/Math/MathML\" xmlns=\"http://www.elsevier.com/xml/ja/dtd\" xmlns:xoe=\"http://www.elsevier.com/xml/xoe/dtd\" xmlns:bk=\"http://www.elsevier.com/xml/bk/dtd\" xmlns:cals=\"http://www.elsevier.com/xml/common/cals/dtd\" xmlns:ce=\"http://www.elsevier.com/xml/common/dtd\" xmlns:ja=\"http://www.elsevier.com/xml/ja/dtd\" xmlns:sa=\"http://www.elsevier.com/xml/common/struct-aff/dtd\" xmlns:sb=\"http://www.elsevier.com/xml/common/struct-bib/dtd\" xmlns:tb=\"http://www.elsevier.com/xml/common/table/dtd\" xmlns:xlink=\"http://www.w3.org/1999/xlink\" xmlns:xocs=\"http://www.elsevier.com/xml/xocs/dtd\" xmlns:dc=\"http://purl.org/dc/elements/1.1/\" xmlns:dcterms=\"http://purl.org/dc/terms/\" xmlns:prism=\"http://prismstandard.org/namespaces/basic/2.0/\" xmlns:xsi=\"http://www.w3.org/2001/XMLSchema-instance\" altimg=\"si90.gif\" overflow=\"scroll\">\n                                 <mml:mrow>\n                                    <mml:msub>\n                                       <mml:mrow>\n                                          <mml:mi>C</mml:mi>\n                                       </mml:mrow>\n                                       <mml:mrow>\n                                          <mml:mi mathvariant=\"normal\">Σ</mml:mi>\n                                       </mml:mrow>\n                                    </mml:msub>\n                                    <mml:mo stretchy=\"false\">(</mml:mo>\n                                    <mml:msub>\n                                       <mml:mrow>\n                                          <mml:mi>u</mml:mi>\n                                       </mml:mrow>\n                                       <mml:mrow>\n                                          <mml:mn>1</mml:mn>\n                                       </mml:mrow>\n                                    </mml:msub>\n                                    <mml:mtext>,</mml:mtext>\n                                    <mml:mo>…</mml:mo>\n                                    <mml:mtext>,</mml:mtext>\n                                    <mml:msub>\n                                       <mml:mrow>\n                                          <mml:mi>u</mml:mi>\n                                       </mml:mrow>\n                                       <mml:mrow>\n                                          <mml:mi>n</mml:mi>\n                                       </mml:mrow>\n                                    </mml:msub>\n                                    <mml:mo stretchy=\"false\">)</mml:mo>\n                                    <mml:mo>=</mml:mo>\n                                    <mml:msub>\n                                       <mml:mrow>\n                                          <mml:mi>Φ</mml:mi>\n                                       </mml:mrow>\n                                       <mml:mrow>\n                                          <mml:mi mathvariant=\"normal\">Σ</mml:mi>\n                                       </mml:mrow>\n                                    </mml:msub>\n                                    <mml:mo stretchy=\"false\">(</mml:mo>\n                                    <mml:msup>\n                                       <mml:mrow>\n                                          <mml:mi>Φ</mml:mi>\n                                       </mml:mrow>\n                                       <mml:mrow>\n                                          <mml:mo>-</mml:mo>\n                                          <mml:mn>1</mml:mn>\n                                       </mml:mrow>\n                                    </mml:msup>\n                                    <mml:mo stretchy=\"false\">(</mml:mo>\n                                    <mml:msub>\n                                       <mml:mrow>\n                                          <mml:mi>u</mml:mi>\n                                       </mml:mrow>\n                                       <mml:mrow>\n                                          <mml:mn>1</mml:mn>\n                                       </mml:mrow>\n                                    </mml:msub>\n                                    <mml:mo stretchy=\"false\">)</mml:mo>\n                                    <mml:mtext>,</mml:mtext>\n                                    <mml:mo>…</mml:mo>\n                                    <mml:mtext>,</mml:mtext>\n                                    <mml:msup>\n                                       <mml:mrow>\n                                          <mml:mi>Φ</mml:mi>\n                                       </mml:mrow>\n                                       <mml:mrow>\n                                          <mml:mo>-</mml:mo>\n                                          <mml:mn>1</mml:mn>\n                                       </mml:mrow>\n                                    </mml:msup>\n                                    <mml:mo stretchy=\"false\">(</mml:mo>\n                                    <mml:msub>\n                                       <mml:mrow>\n                                          <mml:mi>u</mml:mi>\n                                       </mml:mrow>\n                                       <mml:mrow>\n                                          <mml:mi>n</mml:mi>\n                                       </mml:mrow>\n                                    </mml:msub>\n                                    <mml:mo stretchy=\"false\">)</mml:mo>\n                                    <mml:mo stretchy=\"false\">)</mml:mo>\n                                 </mml:mrow>\n                              </mml:math>\n                           ",
      "method": "mathml",
      "status": "unreviewed",
      "confidence": null,
      "source_file": null,
      "note": null
    },
    {
      "id": "eq-0004",
      "label": "e0020",
      "page_start": null,
      "page_end": null,
      "latex": "\\mathit{AIC} = 2 k - 2 ln \\left(L\\right)",
      "mathml": "<mml:math xmlns:mml=\"http://www.w3.org/1998/Math/MathML\" xmlns=\"http://www.elsevier.com/xml/ja/dtd\" xmlns:xoe=\"http://www.elsevier.com/xml/xoe/dtd\" xmlns:bk=\"http://www.elsevier.com/xml/bk/dtd\" xmlns:cals=\"http://www.elsevier.com/xml/common/cals/dtd\" xmlns:ce=\"http://www.elsevier.com/xml/common/dtd\" xmlns:ja=\"http://www.elsevier.com/xml/ja/dtd\" xmlns:sa=\"http://www.elsevier.com/xml/common/struct-aff/dtd\" xmlns:sb=\"http://www.elsevier.com/xml/common/struct-bib/dtd\" xmlns:tb=\"http://www.elsevier.com/xml/common/table/dtd\" xmlns:xlink=\"http://www.w3.org/1999/xlink\" xmlns:xocs=\"http://www.elsevier.com/xml/xocs/dtd\" xmlns:dc=\"http://purl.org/dc/elements/1.1/\" xmlns:dcterms=\"http://purl.org/dc/terms/\" xmlns:prism=\"http://prismstandard.org/namespaces/basic/2.0/\" xmlns:xsi=\"http://www.w3.org/2001/XMLSchema-instance\" altimg=\"si103.gif\" overflow=\"scroll\">\n                                 <mml:mrow>\n                                    <mml:mi mathvariant=\"italic\">AIC</mml:mi>\n                                    <mml:mo>=</mml:mo>\n                                    <mml:mn>2</mml:mn>\n                                    <mml:mi>k</mml:mi>\n                                    <mml:mo>-</mml:mo>\n                                    <mml:mn>2</mml:mn>\n                                    <mml:mi mathvariant=\"normal\">ln</mml:mi>\n                                    <mml:mo stretchy=\"false\">(</mml:mo>\n                                    <mml:mi>L</mml:mi>\n                                    <mml:mo stretchy=\"false\">)</mml:mo>\n                                 </mml:mrow>\n                              </mml:math>\n                           ",
      "method": "mathml",
      "status": "unreviewed",
      "confidence": null,
      "source_file": null,
      "note": null
    },
    {
      "id": "eq-0005",
      "label": "e0030",
      "page_start": null,
      "page_end": null,
      "latex": "U_{1} = \\overset{\\sim}{U}_{1} , U_{2} = C_{\\Sigma_{\\left[1 , 2\\right]}} \\left(\\right. \\overset{\\sim}{U}_{2} \\left|\\right. U_{1} \\left.\\right) , U_{3} = C_{\\Sigma_{\\left[1 , 2 , 3\\right]}} \\left(\\right. \\overset{\\sim}{U}_{3} \\left|\\right. U_{1} , U_{2} \\left.\\right) , U_{4} = C_{\\Sigma} \\left(\\right. \\overset{\\sim}{U}_{4} \\left|\\right. U_{1} , U_{2} , U_{3} \\left.\\right)",
      "mathml": "<mml:math xmlns:mml=\"http://www.w3.org/1998/Math/MathML\" xmlns=\"http://www.elsevier.com/xml/ja/dtd\" xmlns:xoe=\"http://www.elsevier.com/xml/xoe/dtd\" xmlns:bk=\"http://www.elsevier.com/xml/bk/dtd\" xmlns:cals=\"http://www.elsevier.com/xml/common/cals/dtd\" xmlns:ce=\"http://www.elsevier.com/xml/common/dtd\" xmlns:ja=\"http://www.elsevier.com/xml/ja/dtd\" xmlns:sa=\"http://www.elsevier.com/xml/common/struct-aff/dtd\" xmlns:sb=\"http://www.elsevier.com/xml/common/struct-bib/dtd\" xmlns:tb=\"http://www.elsevier.com/xml/common/table/dtd\" xmlns:xlink=\"http://www.w3.org/1999/xlink\" xmlns:xocs=\"http://www.elsevier.com/xml/xocs/dtd\" xmlns:dc=\"http://purl.org/dc/elements/1.1/\" xmlns:dcterms=\"http://purl.org/dc/terms/\" xmlns:prism=\"http://prismstandard.org/namespaces/basic/2.0/\" xmlns:xsi=\"http://www.w3.org/2001/XMLSchema-instance\" altimg=\"si109.gif\" overflow=\"scroll\">\n                                 <mml:mrow>\n                                    <mml:msub>\n                                       <mml:mrow>\n                                          <mml:mi>U</mml:mi>\n                                       </mml:mrow>\n                                       <mml:mrow>\n                                          <mml:mn>1</mml:mn>\n                                       </mml:mrow>\n                                    </mml:msub>\n                                    <mml:mo>=</mml:mo>\n                                    <mml:msub>\n                                       <mml:mrow>\n                                          <mml:mover accent=\"true\">\n                                             <mml:mrow>\n                                                <mml:mi>U</mml:mi>\n                                             </mml:mrow>\n                                             <mml:mrow>\n                                                <mml:mo stretchy=\"true\">∼</mml:mo>\n                                             </mml:mrow>\n                                          </mml:mover>\n                                       </mml:mrow>\n                                       <mml:mrow>\n                                          <mml:mn>1</mml:mn>\n                                       </mml:mrow>\n                                    </mml:msub>\n                                    <mml:mtext>,</mml:mtext>\n                                    <mml:mspace width=\"1em\"/>\n                                    <mml:msub>\n                                       <mml:mrow>\n                                          <mml:mi>U</mml:mi>\n                                       </mml:mrow>\n                                       <mml:mrow>\n                                          <mml:mn>2</mml:mn>\n                                       </mml:mrow>\n                                    </mml:msub>\n                                    <mml:mo>=</mml:mo>\n                                    <mml:msub>\n                                       <mml:mrow>\n                                          <mml:mi>C</mml:mi>\n                                       </mml:mrow>\n                                       <mml:mrow>\n                                          <mml:msub>\n                                             <mml:mrow>\n                                                <mml:mi mathvariant=\"normal\">Σ</mml:mi>\n                                             </mml:mrow>\n                                             <mml:mrow>\n                                                <mml:mo stretchy=\"false\">[</mml:mo>\n                                                <mml:mn>1</mml:mn>\n                                                <mml:mtext>,</mml:mtext>\n                                                <mml:mn>2</mml:mn>\n                                                <mml:mo stretchy=\"false\">]</mml:mo>\n                                             </mml:mrow>\n                                          </mml:msub>\n                                       </mml:mrow>\n                                    </mml:msub>\n                                    <mml:mo stretchy=\"false\">(</mml:mo>\n                                    <mml:msub>\n                                       <mml:mrow>\n                                          <mml:mover accent=\"true\">\n                                             <mml:mrow>\n                                                <mml:mi>U</mml:mi>\n                                             </mml:mrow>\n                                             <mml:mrow>\n                                                <mml:mo stretchy=\"true\">∼</mml:mo>\n                                             </mml:mrow>\n                                          </mml:mover>\n                                       </mml:mrow>\n                                       <mml:mrow>\n                                          <mml:mn>2</mml:mn>\n                                       </mml:mrow>\n                                    </mml:msub>\n                                    <mml:mo stretchy=\"false\">|</mml:mo>\n                                    <mml:msub>\n                                       <mml:mrow>\n                                          <mml:mi>U</mml:mi>\n                                       </mml:mrow>\n                                       <mml:mrow>\n                                          <mml:mn>1</mml:mn>\n                                       </mml:mrow>\n                                    </mml:msub>\n                                    <mml:mo stretchy=\"false\">)</mml:mo>\n                                    <mml:mtext>,</mml:mtext>\n                                    <mml:mspace width=\"1em\"/>\n                                    <mml:msub>\n                                       <mml:mrow>\n                                          <mml:mi>U</mml:mi>\n                                       </mml:mrow>\n                                       <mml:mrow>\n                                          <mml:mn>3</mml:mn>\n                                       </mml:mrow>\n                                    </mml:msub>\n                                    <mml:mo>=</mml:mo>\n                                    <mml:msub>\n                                       <mml:mrow>\n                                          <mml:mi>C</mml:mi>\n                                       </mml:mrow>\n                                       <mml:mrow>\n                                          <mml:msub>\n                                             <mml:mrow>\n                                                <mml:mi mathvariant=\"normal\">Σ</mml:mi>\n                                             </mml:mrow>\n                                             <mml:mrow>\n                                                <mml:mo stretchy=\"false\">[</mml:mo>\n                                                <mml:mn>1</mml:mn>\n                                                <mml:mtext>,</mml:mtext>\n                                                <mml:mn>2</mml:mn>\n                                                <mml:mtext>,</mml:mtext>\n                                                <mml:mn>3</mml:mn>\n                                                <mml:mo stretchy=\"false\">]</mml:mo>\n                                             </mml:mrow>\n                                          </mml:msub>\n                                       </mml:mrow>\n                                    </mml:msub>\n                                    <mml:mo stretchy=\"false\">(</mml:mo>\n                                    <mml:msub>\n                                       <mml:mrow>\n                                          <mml:mover accent=\"true\">\n                                             <mml:mrow>\n                                                <mml:mi>U</mml:mi>\n                                             </mml:mrow>\n                                             <mml:mrow>\n                                                <mml:mo stretchy=\"true\">∼</mml:mo>\n                                             </mml:mrow>\n                                          </mml:mover>\n                                       </mml:mrow>\n                                       <mml:mrow>\n                                          <mml:mn>3</mml:mn>\n                                       </mml:mrow>\n                                    </mml:msub>\n                                    <mml:mo stretchy=\"false\">|</mml:mo>\n                                    <mml:msub>\n                                       <mml:mrow>\n                                          <mml:mi>U</mml:mi>\n                                       </mml:mrow>\n                                       <mml:mrow>\n                                          <mml:mn>1</mml:mn>\n                                       </mml:mrow>\n                                    </mml:msub>\n                                    <mml:mtext>,</mml:mtext>\n                                    <mml:msub>\n                                       <mml:mrow>\n                                          <mml:mi>U</mml:mi>\n                                       </mml:mrow>\n                                       <mml:mrow>\n                                          <mml:mn>2</mml:mn>\n                                       </mml:mrow>\n                                    </mml:msub>\n                                    <mml:mo stretchy=\"false\">)</mml:mo>\n                                    <mml:mtext>,</mml:mtext>\n                                    <mml:mspace width=\"1em\"/>\n                                    <mml:msub>\n                                       <mml:mrow>\n                                          <mml:mi>U</mml:mi>\n                                       </mml:mrow>\n                                       <mml:mrow>\n                                          <mml:mn>4</mml:mn>\n                                       </mml:mrow>\n                                    </mml:msub>\n                                    <mml:mo>=</mml:mo>\n                                    <mml:msub>\n                                       <mml:mrow>\n                                          <mml:mi>C</mml:mi>\n                                       </mml:mrow>\n                                       <mml:mrow>\n                                          <mml:mi mathvariant=\"normal\">Σ</mml:mi>\n                                       </mml:mrow>\n                                    </mml:msub>\n                                    <mml:mo stretchy=\"false\">(</mml:mo>\n                                    <mml:msub>\n                                       <mml:mrow>\n                                          <mml:mover accent=\"true\">\n                                             <mml:mrow>\n                                                <mml:mi>U</mml:mi>\n                                             </mml:mrow>\n                                             <mml:mrow>\n                                                <mml:mo stretchy=\"true\">∼</mml:mo>\n                                             </mml:mrow>\n                                          </mml:mover>\n                                       </mml:mrow>\n                                       <mml:mrow>\n                                          <mml:mn>4</mml:mn>\n                                       </mml:mrow>\n                                    </mml:msub>\n                                    <mml:mo stretchy=\"false\">|</mml:mo>\n                                    <mml:msub>\n                                       <mml:mrow>\n                                          <mml:mi>U</mml:mi>\n                                       </mml:mrow>\n                                       <mml:mrow>\n                                          <mml:mn>1</mml:mn>\n                                       </mml:mrow>\n                                    </mml:msub>\n                                    <mml:mtext>,</mml:mtext>\n                                    <mml:msub>\n                                       <mml:mrow>\n                                          <mml:mi>U</mml:mi>\n                                       </mml:mrow>\n                                       <mml:mrow>\n                                          <mml:mn>2</mml:mn>\n                                       </mml:mrow>\n                                    </mml:msub>\n                                    <mml:mtext>,</mml:mtext>\n                                    <mml:msub>\n                                       <mml:mrow>\n                                          <mml:mi>U</mml:mi>\n                                       </mml:mrow>\n                                       <mml:mrow>\n                                          <mml:mn>3</mml:mn>\n                                       </mml:mrow>\n                                    </mml:msub>\n                                    <mml:mo stretchy=\"false\">)</mml:mo>\n                                 </mml:mrow>\n                              </mml:math>\n                           ",
      "method": "mathml",
      "status": "unreviewed",
      "confidence": null,
      "source_file": null,
      "note": null
    },
    {
      "id": "eq-0006",
      "label": "e0025",
      "page_start": null,
      "page_end": null,
      "latex": "V = \\left(\\Phi^{- 1} \\left(U_{1}\\right)\\right)^{2} + \\left(\\Phi^{- 1} \\left(U_{2}\\right)\\right)^{2} + \\left(\\Phi^{- 1} \\left(U_{3}\\right)\\right)^{2} + \\left(\\Phi^{- 1} \\left(U_{4}\\right)\\right)^{2}",
      "mathml": "<mml:math xmlns:mml=\"http://www.w3.org/1998/Math/MathML\" xmlns=\"http://www.elsevier.com/xml/ja/dtd\" xmlns:xoe=\"http://www.elsevier.com/xml/xoe/dtd\" xmlns:bk=\"http://www.elsevier.com/xml/bk/dtd\" xmlns:cals=\"http://www.elsevier.com/xml/common/cals/dtd\" xmlns:ce=\"http://www.elsevier.com/xml/common/dtd\" xmlns:ja=\"http://www.elsevier.com/xml/ja/dtd\" xmlns:sa=\"http://www.elsevier.com/xml/common/struct-aff/dtd\" xmlns:sb=\"http://www.elsevier.com/xml/common/struct-bib/dtd\" xmlns:tb=\"http://www.elsevier.com/xml/common/table/dtd\" xmlns:xlink=\"http://www.w3.org/1999/xlink\" xmlns:xocs=\"http://www.elsevier.com/xml/xocs/dtd\" xmlns:dc=\"http://purl.org/dc/elements/1.1/\" xmlns:dcterms=\"http://purl.org/dc/terms/\" xmlns:prism=\"http://prismstandard.org/namespaces/basic/2.0/\" xmlns:xsi=\"http://www.w3.org/2001/XMLSchema-instance\" altimg=\"si116.gif\" overflow=\"scroll\">\n                                 <mml:mrow>\n                                    <mml:mi>V</mml:mi>\n                                    <mml:mo>=</mml:mo>\n                                    <mml:msup>\n                                       <mml:mrow>\n                                          <mml:mfenced open=\"(\" close=\")\">\n                                             <mml:mrow>\n                                                <mml:msup>\n                                                   <mml:mrow>\n                                                      <mml:mi>Φ</mml:mi>\n                                                   </mml:mrow>\n                                                   <mml:mrow>\n                                                      <mml:mo>-</mml:mo>\n                                                      <mml:mn>1</mml:mn>\n                                                   </mml:mrow>\n                                                </mml:msup>\n                                                <mml:mo stretchy=\"false\">(</mml:mo>\n                                                <mml:msub>\n                                                   <mml:mrow>\n                                                      <mml:mi>U</mml:mi>\n                                                   </mml:mrow>\n                                                   <mml:mrow>\n                                                      <mml:mn>1</mml:mn>\n                                                   </mml:mrow>\n                                                </mml:msub>\n                                                <mml:mo stretchy=\"false\">)</mml:mo>\n                                             </mml:mrow>\n                                          </mml:mfenced>\n                                       </mml:mrow>\n                                       <mml:mrow>\n                                          <mml:mn>2</mml:mn>\n                                       </mml:mrow>\n                                    </mml:msup>\n                                    <mml:mo>+</mml:mo>\n                                    <mml:msup>\n                                       <mml:mrow>\n                                          <mml:mfenced open=\"(\" close=\")\">\n                                             <mml:mrow>\n                                                <mml:msup>\n                                                   <mml:mrow>\n                                                      <mml:mi>Φ</mml:mi>\n                                                   </mml:mrow>\n                                                   <mml:mrow>\n                                                      <mml:mo>-</mml:mo>\n                                                      <mml:mn>1</mml:mn>\n                                                   </mml:mrow>\n                                                </mml:msup>\n                                                <mml:mo stretchy=\"false\">(</mml:mo>\n                                                <mml:msub>\n                                                   <mml:mrow>\n                                                      <mml:mi>U</mml:mi>\n                                                   </mml:mrow>\n                                                   <mml:mrow>\n                                                      <mml:mn>2</mml:mn>\n                                                   </mml:mrow>\n                                                </mml:msub>\n                                                <mml:mo stretchy=\"false\">)</mml:mo>\n                                             </mml:mrow>\n                                          </mml:mfenced>\n                                       </mml:mrow>\n                                       <mml:mrow>\n                                          <mml:mn>2</mml:mn>\n                                       </mml:mrow>\n                                    </mml:msup>\n                                    <mml:mo>+</mml:mo>\n                                    <mml:msup>\n                                       <mml:mrow>\n                                          <mml:mfenced open=\"(\" close=\")\">\n                                             <mml:mrow>\n                                                <mml:msup>\n                                                   <mml:mrow>\n                                                      <mml:mi>Φ</mml:mi>\n                                                   </mml:mrow>\n                                                   <mml:mrow>\n                                                      <mml:mo>-</mml:mo>\n                                                      <mml:mn>1</mml:mn>\n                                                   </mml:mrow>\n                                                </mml:msup>\n                                                <mml:mo stretchy=\"false\">(</mml:mo>\n                                                <mml:msub>\n                                                   <mml:mrow>\n                                                      <mml:mi>U</mml:mi>\n                                                   </mml:mrow>\n                                                   <mml:mrow>\n                                                      <mml:mn>3</mml:mn>\n                                                   </mml:mrow>\n                                                </mml:msub>\n                                                <mml:mo stretchy=\"false\">)</mml:mo>\n                                             </mml:mrow>\n                                          </mml:mfenced>\n                                       </mml:mrow>\n                                       <mml:mrow>\n                                          <mml:mn>2</mml:mn>\n                                       </mml:mrow>\n                                    </mml:msup>\n                                    <mml:mo>+</mml:mo>\n                                    <mml:msup>\n                                       <mml:mrow>\n                                          <mml:mfenced open=\"(\" close=\")\">\n                                             <mml:mrow>\n                                                <mml:msup>\n                                                   <mml:mrow>\n                                                      <mml:mi>Φ</mml:mi>\n                                                   </mml:mrow>\n                                                   <mml:mrow>\n                                                      <mml:mo>-</mml:mo>\n                                                      <mml:mn>1</mml:mn>\n                                                   </mml:mrow>\n                                                </mml:msup>\n                                                <mml:mo stretchy=\"false\">(</mml:mo>\n                                                <mml:msub>\n                                                   <mml:mrow>\n                                                      <mml:mi>U</mml:mi>\n                                                   </mml:mrow>\n                                                   <mml:mrow>\n                                                      <mml:mn>4</mml:mn>\n                                                   </mml:mrow>\n                                                </mml:msub>\n                                                <mml:mo stretchy=\"false\">)</mml:mo>\n                                             </mml:mrow>\n                                          </mml:mfenced>\n                                       </mml:mrow>\n                                       <mml:mrow>\n                                          <mml:mn>2</mml:mn>\n                                       </mml:mrow>\n                                    </mml:msup>\n                                 </mml:mrow>\n                              </mml:math>\n                           ",
      "method": "mathml",
      "status": "unreviewed",
      "confidence": null,
      "source_file": null,
      "note": null
    }
  ]
}
